fractrics/MSM.py
fractrics/__about__.py
fractrics/__init__.py
fractrics/diagnostics.py
fractrics/nelder_mead.py
fractrics/unscent_KF.py
fractrics/utilities.py
fractrics/_components/__init__.py
fractrics/_components/core.py
fractrics/_components/HMM/__init__.py
fractrics/_components/HMM/base.py
fractrics/_components/HMM/data_likelihood.py
fractrics/_components/HMM/forward.py
fractrics/_components/HMM/initial_distribution.py
fractrics/_components/HMM/transition_tensor.py
fractrics/_components/_pending_refactor/README.md
fractrics/_components/_pending_refactor/_DTSM.py
fractrics/_components/_pending_refactor/_ar.py
fractrics/_components/_pending_refactor/_descriptive.py
fractrics/_components/_pending_refactor/_helper.py
fractrics/_components/_pending_refactor/_levelMSM.py
fractrics-0.3.0.dist-info/METADATA
fractrics-0.3.0.dist-info/WHEEL
fractrics-0.3.0.dist-info/licenses/LICENSE
fractrics-0.3.0.dist-info/RECORD
