Metadata-Version: 2.4
Name: fractrics
Version: 0.3.0
Summary: A fractal econometrics package for python, built with JAX.
Project-URL: Documentation, https://github.com/AlfredoDiodati/fractrics#readme
Project-URL: Issues, https://github.com/AlfredoDiodati/fractrics/issues
Project-URL: Source, https://github.com/AlfredoDiodati/fractrics
Author-email: Alfredo Diodati <diodatialfredo@gmail.com>
License-Expression: MIT
License-File: LICENSE
Classifier: Development Status :: 4 - Beta
Classifier: Programming Language :: Python
Classifier: Programming Language :: Python :: 3.11
Classifier: Programming Language :: Python :: Implementation :: CPython
Requires-Python: >=3.11
Requires-Dist: jax==0.7.2
Requires-Dist: matplotlib==3.10.6
Requires-Dist: numpy==2.3.3
Requires-Dist: pandas==2.3.3
